odoo/addons/web_search_with_and/README.rst
odoo/addons/web_search_with_and/__init__.py
odoo/addons/web_search_with_and/__manifest__.py
odoo/addons/web_search_with_and/i18n/es.po
odoo/addons/web_search_with_and/i18n/it.po
odoo/addons/web_search_with_and/i18n/pt.po
odoo/addons/web_search_with_and/i18n/web_search_with_and.pot
odoo/addons/web_search_with_and/readme/CONTRIBUTORS.rst
odoo/addons/web_search_with_and/readme/DESCRIPTION.rst
odoo/addons/web_search_with_and/readme/USAGE.rst
odoo/addons/web_search_with_and/static/description/icon.png
odoo/addons/web_search_with_and/static/description/index.html
odoo/addons/web_search_with_and/static/src/js/control_panel_model_extension.js
odoo/addons/web_search_with_and/static/src/js/search_bar.js
odoo/addons/web_search_with_and/views/assets.xml
odoo14_addon_web_search_with_and-14.0.1.0.1.dist-info/METADATA
odoo14_addon_web_search_with_and-14.0.1.0.1.dist-info/WHEEL
odoo14_addon_web_search_with_and-14.0.1.0.1.dist-info/top_level.txt
odoo14_addon_web_search_with_and-14.0.1.0.1.dist-info/RECORD
